access_distributor/__init__.py
access_distributor/accounts/__init__.py
access_distributor/accounts/claim_status.py
access_distributor/accounts/merkle_distributor.py
access_distributor/errors/__init__.py
access_distributor/errors/anchor.py
access_distributor/errors/custom.py
access_distributor/instructions/__init__.py
access_distributor/instructions/claim_locked.py
access_distributor/instructions/clawback.py
access_distributor/instructions/new_claim.py
access_distributor/instructions/new_distributor.py
access_distributor/instructions/set_admin.py
access_distributor/instructions/withdraw_custody_sol.py
access_distributor/program_id.py
access_distributor-1.0.5.dist-info/METADATA
access_distributor-1.0.5.dist-info/WHEEL
access_distributor-1.0.5.dist-info/RECORD
