Metadata-Version: 2.3
Name: access-distributor
Version: 1.0.5
Summary: Python bindings for the Access Distributor Solana program
Author: Access Labs
Author-email: vladislav@accessprotocol.co
Requires-Python: >=3.9,<4.0.0
Classifier: Programming Language :: Python :: 3
Classifier: Programming Language :: Python :: 3.9
Classifier: Programming Language :: Python :: 3.10
Classifier: Programming Language :: Python :: 3.11
Classifier: Programming Language :: Python :: 3.12
Classifier: Programming Language :: Python :: 3.13
Requires-Dist: anchorpy
Requires-Dist: borsh-construct
Requires-Dist: pytest-asyncio (>=1.0.0,<2.0.0)
Requires-Dist: solders
Project-URL: Repository, https://github.com/Access-Labs-Inc/distributor
